setup.cfg
setup.py
pydipankar/SimpleStore.py
pydipankar/Spider.py
pydipankar/__init__.py
pydipankar.egg-info/PKG-INFO
pydipankar.egg-info/SOURCES.txt
pydipankar.egg-info/dependency_links.txt
pydipankar.egg-info/entry_points.txt
pydipankar.egg-info/not-zip-safe
pydipankar.egg-info/requires.txt
pydipankar.egg-info/top_level.txt