Metadata-Version: 1.0
Name: pydipankar
Version: 1.2.2
Summary: Common lib used by Dipoankar
Home-page: UNKNOWN
Author: dipankar
Author-email: ddutta@microsoft.com
License: UNKNOWN
Keywords: dipankar spider common lib experimenet
Platform: UNKNOWN
